pest/__init__.py
pest/checkpoint_int.py
pest/exceptions.py
pest/grammar/__init__.py
pest/grammar/codegen/__init__.py
pest/grammar/codegen/builder.py
pest/grammar/codegen/generate.py
pest/grammar/exceptions.py
pest/grammar/expression.py
pest/grammar/expressions/__init__.py
pest/grammar/expressions/choice.py
pest/grammar/expressions/group.py
pest/grammar/expressions/postfix.py
pest/grammar/expressions/prefix.py
pest/grammar/expressions/sequence.py
pest/grammar/expressions/terminals.py
pest/grammar/optimizer.py
pest/grammar/optimizers/__init__.py
pest/grammar/optimizers/inliners.py
pest/grammar/optimizers/skippers.py
pest/grammar/optimizers/squash_choice.py
pest/grammar/optimizers/unroller.py
pest/grammar/parser.py
pest/grammar/rule.py
pest/grammar/rules/__init__.py
pest/grammar/rules/ascii.py
pest/grammar/rules/special.py
pest/grammar/rules/unicode.py
pest/grammar/scanner.py
pest/grammar/tokens.py
pest/grammar/unescape.py
pest/pairs.py
pest/parser.py
pest/pratt.py
pest/py.typed
pest/stack.py
pest/state.py
python_pest-0.1.1.dist-info/WHEEL
python_pest-0.1.1.dist-info/METADATA
python_pest-0.1.1.dist-info/RECORD
