Metadata-Version: 2.3
Name: python-pest
Version: 0.1.1
Summary: A general purpose parser written in Python.
Author: James Prior
Author-email: James Prior <jamesgr.prior@gmail.com>
Classifier: Development Status :: 4 - Beta
Classifier: License :: OSI Approved :: MIT License
Classifier: Programming Language :: Python
Classifier: Programming Language :: Python :: 3.11
Classifier: Programming Language :: Python :: 3.12
Classifier: Programming Language :: Python :: 3.13
Classifier: Programming Language :: Python :: 3.14
Classifier: Programming Language :: Python :: Implementation :: CPython
Classifier: Programming Language :: Python :: Implementation :: PyPy
Requires-Dist: regex>=2025.7.34
Requires-Python: >=3.11
Project-URL: Documentation, https://jg-rp.github.io/python-pest/
Project-URL: Issues, https://github.com/jg-rp/python-pest/issues
Project-URL: Source, https://github.com/jg-rp/python-pest
